inforion/__init__.py
inforion/__main__.py
inforion/__version.py
inforion/_version.py
inforion/dynamic_.py
inforion/infor.py
inforion/m3_fields_info.db
inforion/test.py
inforion/datacatalog/__init__.py
inforion/datacatalog/datacatalog.py
inforion/datalake/__init__.py
inforion/datalake/datalake.py
inforion/excelexport/11072020.zip
inforion/excelexport/Mapping_Template.xlsx
inforion/excelexport/__init__.py
inforion/excelexport/api-files/InforM3MIv2 (1).json
inforion/excelexport/api-files/InforM3MIv2 (10).json
inforion/excelexport/api-files/InforM3MIv2 (100).json
inforion/excelexport/api-files/InforM3MIv2 (11).json
inforion/excelexport/api-files/InforM3MIv2 (12).json
inforion/excelexport/api-files/InforM3MIv2 (13).json
inforion/excelexport/api-files/InforM3MIv2 (14).json
inforion/excelexport/api-files/InforM3MIv2 (15).json
inforion/excelexport/api-files/InforM3MIv2 (16).json
inforion/excelexport/api-files/InforM3MIv2 (17).json
inforion/excelexport/api-files/InforM3MIv2 (18).json
inforion/excelexport/api-files/InforM3MIv2 (19).json
inforion/excelexport/api-files/InforM3MIv2 (2).json
inforion/excelexport/api-files/InforM3MIv2 (20).json
inforion/excelexport/api-files/InforM3MIv2 (21).json
inforion/excelexport/api-files/InforM3MIv2 (22).json
inforion/excelexport/api-files/InforM3MIv2 (23).json
inforion/excelexport/api-files/InforM3MIv2 (24).json
inforion/excelexport/api-files/InforM3MIv2 (25).json
inforion/excelexport/api-files/InforM3MIv2 (26).json
inforion/excelexport/api-files/InforM3MIv2 (27).json
inforion/excelexport/api-files/InforM3MIv2 (28).json
inforion/excelexport/api-files/InforM3MIv2 (29).json
inforion/excelexport/api-files/InforM3MIv2 (3).json
inforion/excelexport/api-files/InforM3MIv2 (30).json
inforion/excelexport/api-files/InforM3MIv2 (31).json
inforion/excelexport/api-files/InforM3MIv2 (32).json
inforion/excelexport/api-files/InforM3MIv2 (33).json
inforion/excelexport/api-files/InforM3MIv2 (34).json
inforion/excelexport/api-files/InforM3MIv2 (35).json
inforion-2.26.2.4.dist-info/inforion.egg-info/dependency_links.txt
inforion-2.26.2.4.dist-info/inforion.egg-info/entry_points.txt
inforion-2.26.2.4.dist-info/inforion.egg-info/top_level.txt
inforion-2.26.2.4.dist-info/inforion.egg-info/zip-safe
inforion-2.26.2.4.dist-info/inforion.egg-info/inforion.egg-info/dependency_links.txt
inforion-2.26.2.4.dist-info/inforion.egg-info/inforion.egg-info/entry_points.txt
inforion-2.26.2.4.dist-info/inforion.egg-info/inforion.egg-info/top_level.txt
inforion-2.26.2.4.dist-info/inforion.egg-info/inforion.egg-info/zip-safe
inforion-2.26.2.4.dist-info/LICENSE
inforion-2.26.2.4.dist-info/METADATA
inforion-2.26.2.4.dist-info/WHEEL
inforion-2.26.2.4.dist-info/entry_points.txt
inforion-2.26.2.4.dist-info/top_level.txt
inforion-2.26.2.4.dist-info/zip-safe
inforion-2.26.2.4.dist-info/RECORD
