Metadata-Version: 2.1
Name: inforion
Version: 2.26.2.4
Summary: Infor ION Package for Python
Home-page: https://github.com/Fellow-Consulting-AG/inforion/
Author: Daniel Jordan
Author-email: daniel.jordan@fellow-consulting.de
License: UNKNOWN
Keywords: Infor,InforION,Datalake,LN,M3
Platform: UNKNOWN
Classifier: Programming Language :: Python :: 3
Classifier: License :: OSI Approved :: MIT License
Classifier: Operating System :: OS Independent
Requires-Python: >=3.7
Requires-Dist: click (==7.1.2)
Requires-Dist: curlify (==2.2.1)
Requires-Dist: dload (==0.6)
Requires-Dist: logger (==1.4)
Requires-Dist: numpy (==1.19.0)
Requires-Dist: oauthlib (==3.1.0)
Requires-Dist: openpyxl (==3.0.4)
Requires-Dist: pandas (==1.1.1)
Requires-Dist: progressbar2 (==3.51.4)
Requires-Dist: pytest (==5.4.3)
Requires-Dist: requests (==2.24.0)
Requires-Dist: requests-oauthlib (==1.3.0)
Requires-Dist: requests-toolbelt (==0.9.1)
Requires-Dist: urllib3 (==1.25.9)
Requires-Dist: validators (==0.16.0)
Requires-Dist: XlsxWriter (==1.2.9)
Requires-Dist: setuptools (~=49.2.0)
Requires-Dist: xlrd (==1.2.0)
Requires-Dist: PyYAML (==5.3.1)
Requires-Dist: pyodbc (==4.0.30)
